qaeval/__init__.py
qaeval/answer_selection.py
qaeval/metric.py
qaeval/answering/__init__.py
qaeval/answering/model.py
qaeval/answering/utils.py
qaeval/answering/__pycache__/__init__.cpython-38.pyc
qaeval/answering/__pycache__/__init__.cpython-39.pyc
qaeval/answering/__pycache__/utils.cpython-38.pyc
qaeval/answering/__pycache__/utils.cpython-39.pyc
qaeval/generation/__init__.py
qaeval/generation/model.py
qaeval/generation/util.py
qaeval/generation/__pycache__/__init__.cpython-38.pyc
qaeval/generation/__pycache__/__init__.cpython-39.pyc
qaeval/generation/__pycache__/util.cpython-38.pyc
qaeval/generation/__pycache__/util.cpython-39.pyc
qaeval/scoring/__init__.py
qaeval/scoring/scorers/__init__.py
qaeval/scoring/scorers/em.py
qaeval/scoring/scorers/f1.py
qaeval/scoring/scorers/is_answered.py
qaeval/scoring/scorers/lerc.py
qaeval/scoring/scorers/meta.py
qaeval/scoring/scorers/scorer.py
plainqafact-0.12.0.dist-info/LICENSE
plainqafact-0.12.0.dist-info/METADATA
plainqafact-0.12.0.dist-info/WHEEL
plainqafact-0.12.0.dist-info/entry_points.txt
plainqafact-0.12.0.dist-info/top_level.txt
plainqafact-0.12.0.dist-info/RECORD
