Metadata-Version: 2.2
Name: plainqafact
Version: 0.12.0
Summary: A framework for evaluating plain language summaries using question answering
Home-page: https://github.com/zhiwenyou103/PlainQAFact
Author: Zhiwen You
Author-email: zhiweny2@illinois.edu
Classifier: Development Status :: 3 - Alpha
Classifier: Intended Audience :: Science/Research
Classifier: License :: OSI Approved :: MIT License
Classifier: Programming Language :: Python :: 3
Classifier: Programming Language :: Python :: 3.9
Requires-Python: >=3.9
License-File: LICENSE
Requires-Dist: faiss-cpu==1.7.4
Requires-Dist: python-liquid==1.10.2
Requires-Dist: langchain==0.0.345
Requires-Dist: tqdm==4.66.1
Requires-Dist: transformers==4.44.2
Requires-Dist: pyserini==0.22.1
Requires-Dist: tiktoken==0.6.0
Requires-Dist: datasets==2.16.1
Requires-Dist: lightgbm==4.5.0
Requires-Dist: torch
Requires-Dist: torchvision
Requires-Dist: torchaudio
Requires-Dist: openai
Requires-Dist: bert-score==0.3.13
Requires-Dist: sentence-transformers==3.4.1
Requires-Dist: edlib==1.3.9.post1
Requires-Dist: overrides==7.7.0
Requires-Dist: spacy==3.7.5
Requires-Dist: sentencepiece==0.2.0
Requires-Dist: sacremoses==0.1.1
Requires-Dist: gdown
Dynamic: author
Dynamic: author-email
Dynamic: classifier
Dynamic: description
Dynamic: description-content-type
Dynamic: home-page
Dynamic: requires-dist
Dynamic: requires-python
Dynamic: summary
